thermostate/__init__.py
thermostate/abbreviations.py
thermostate/plotting.py
thermostate/thermostate.py
thermostate-2.0.0.post1.dist-info/WHEEL
thermostate-2.0.0.post1.dist-info/METADATA
thermostate-2.0.0.post1.dist-info/licenses/LICENSE.md
thermostate-2.0.0.post1.dist-info/RECORD
