Metadata-Version: 2.1
Name: thermostate
Version: 2.0.0.post1
Summary: A package to manage thermodynamic states
License: BSD-3-clause
Keywords: thermodynamics,chemistry,state,education
Author: Bryan W. Weber
Maintainer-email: Bryan W. Weber <bryan.w.weber@gmail.com>
Requires-Python: >=3.9
Classifier: Development Status :: 5 - Production/Stable
Classifier: License :: OSI Approved :: BSD License
Classifier: Operating System :: MacOS
Classifier: Operating System :: MacOS :: MacOS X
Classifier: Operating System :: Microsoft
Classifier: Operating System :: Microsoft :: Windows
Classifier: Operating System :: Microsoft :: Windows :: Windows 10
Classifier: Operating System :: Microsoft :: Windows :: Windows 11
Classifier: Operating System :: POSIX
Classifier: Operating System :: POSIX :: Linux
Classifier: Programming Language :: Python :: 3
Classifier: Programming Language :: Python :: 3.10
Classifier: Programming Language :: Python :: 3.11
Classifier: Programming Language :: Python :: 3.9
Requires-Dist: coolprop>=6.4.3.post1
Requires-Dist: matplotlib>=3.5
Requires-Dist: numpy>=1.22
Requires-Dist: pint<1.0,>=0.20
Provides-Extra: docs
Requires-Dist: ipykernel~=6.21; extra == "docs"
Requires-Dist: ipython~=8.10; extra == "docs"
Requires-Dist: jupyter-client~=8.0; extra == "docs"
Requires-Dist: nbsphinx~=0.8; extra == "docs"
Requires-Dist: recommonmark~=0.7; extra == "docs"
Requires-Dist: sphinx~=6.1; extra == "docs"
Project-URL: Homepage, https://thermostate.readthedocs.io/
Project-URL: Source, https://github.com/bryanwweber/thermostate
Project-URL: Tracker, https://github.com/bryanwweber/thermostate/issues
